CHANGES.txt
DEPENDENCES.txt
README.txt
setup.py
src/ng/__init__.py
src/ng.skin.crosswiki.egg-info/PKG-INFO
src/ng.skin.crosswiki.egg-info/SOURCES.txt
src/ng.skin.crosswiki.egg-info/dependency_links.txt
src/ng.skin.crosswiki.egg-info/namespace_packages.txt
src/ng.skin.crosswiki.egg-info/not-zip-safe
src/ng.skin.crosswiki.egg-info/requires.txt
src/ng.skin.crosswiki.egg-info/top_level.txt
src/ng/skin/__init__.py
src/ng/skin/crosswiki/__init__.py
src/ng/skin/crosswiki/configure.zcml
src/ng/skin/crosswiki/interfaces.py
src/ng/skin/crosswiki/ng.skin.crosswiki.txt
src/ng/skin/crosswiki/etc/ng.skin.crosswiki-configure.zcml
src/ng/skin/crosswiki/images/bottomlogo.png
src/ng/skin/crosswiki/images/logo.gif
src/ng/skin/crosswiki/images/logo.xcf
src/ng/skin/crosswiki/images/toplogo.png
src/ng/skin/crosswiki/page/__init__.py
src/ng/skin/crosswiki/page/configure.zcml
src/ng/skin/crosswiki/page/main/__init__.py
src/ng/skin/crosswiki/page/main/configure.zcml
src/ng/skin/crosswiki/page/main/main.css
src/ng/skin/crosswiki/page/main/main.pt
src/ng/skin/crosswiki/page/main/main.py
src/ng/skin/crosswiki/page/search/__init__.py
src/ng/skin/crosswiki/page/search/configure.zcml
src/ng/skin/crosswiki/page/search/interfaces.py
src/ng/skin/crosswiki/page/search/search.css
src/ng/skin/crosswiki/page/search/searchpage.pt
src/ng/skin/crosswiki/page/search/searchpage.py
src/ng/skin/crosswiki/page/wiki/__init__.py
src/ng/skin/crosswiki/page/wiki/configure.zcml
src/ng/skin/crosswiki/page/wiki/dictionaryitem.py
src/ng/skin/crosswiki/page/wiki/dictionaryreferenceadapter.py
src/ng/skin/crosswiki/page/wiki/interfaces.py
src/ng/skin/crosswiki/page/wiki/nexturl.py